osp/__init__.py
osp/dictionaries/__init__.py
osp/dictionaries/ams/__init__.py
osp/dictionaries/ams/co_pt111_from_meso.json
osp/dictionaries/ams/co_pt111_full.json
osp/dictionaries/catalyticFoam/COModel.json
osp/dictionaries/catalyticFoam/__init__.py
osp/dictionaries/catalyticFoam/laminar_2D_ML/CatalyticReactors
osp/dictionaries/catalyticFoam/laminar_2D_ML/ml_ExtraTrees_forCFD.pkl
osp/dictionaries/catalyticFoam/laminar_2D_ML/0/Rh_s_
osp/dictionaries/catalyticFoam/laminar_2D_ML/0/T
osp/dictionaries/catalyticFoam/laminar_2D_ML/0/U
osp/dictionaries/catalyticFoam/laminar_2D_ML/0/Ydefault
osp/dictionaries/catalyticFoam/laminar_2D_ML/0/p
osp/dictionaries/catalyticFoam/laminar_2D_ML/0/thetaDefault
osp/dictionaries/catalyticFoam/laminar_2D_ML/constant/g
osp/dictionaries/catalyticFoam/laminar_2D_ML/constant/isatOptions
osp/dictionaries/catalyticFoam/laminar_2D_ML/constant/solverOptions
osp/dictionaries/catalyticFoam/laminar_2D_ML/constant/thermophysicalProperties
osp/dictionaries/catalyticFoam/laminar_2D_ML/constant/turbulenceProperties
osp/dictionaries/catalyticFoam/laminar_2D_ML/constant/polyMesh/boundary
osp/dictionaries/catalyticFoam/laminar_2D_ML/constant/polyMesh/faces
osp/dictionaries/catalyticFoam/laminar_2D_ML/constant/polyMesh/neighbour
osp/dictionaries/catalyticFoam/laminar_2D_ML/constant/polyMesh/owner
osp/dictionaries/catalyticFoam/laminar_2D_ML/constant/polyMesh/points
osp/dictionaries/catalyticFoam/laminar_2D_ML/kinetic/Kinetic.kin
osp/dictionaries/catalyticFoam/laminar_2D_ML/kinetic/Surface.sur
osp/dictionaries/catalyticFoam/laminar_2D_ML/kinetic/kinetics/Kinetics_Summary.out
osp/dictionaries/catalyticFoam/laminar_2D_ML/kinetic/kinetics/SurfaceSummary.out
osp/dictionaries/catalyticFoam/laminar_2D_ML/kinetic/kinetics/Thermodynamics_Coefficients.out
osp/dictionaries/catalyticFoam/laminar_2D_ML/kinetic/kinetics/Thermodynamics_Tables.out
osp/dictionaries/catalyticFoam/laminar_2D_ML/kinetic/kinetics/kineticOF
simphony_catalytic-1.4.0.dist-info/LICENSE
simphony_catalytic-1.4.0.dist-info/METADATA
simphony_catalytic-1.4.0.dist-info/WHEEL
simphony_catalytic-1.4.0.dist-info/top_level.txt
simphony_catalytic-1.4.0.dist-info/RECORD
