Metadata-Version: 2.1
Name: simphony-catalytic
Version: 1.4.0
Summary: SimPhoNy wrapper for CatalyticFoam
Author: Matthias Büschelberger
License: GPL-3
Keywords: simphony,cuds,OpenFOAM,CatalyticFoam,ReaxPro
Classifier: Development Status :: 2 - Pre-Alpha
Classifier: License :: OSI Approved :: BSD License
Classifier: Programming Language :: Python :: 3
Classifier: Programming Language :: Python :: 3 :: Only
Classifier: Programming Language :: Python :: Implementation :: CPython
Requires-Python: <3.11,>3.7
License-File: LICENSE
Requires-Dist: pydantic <2.0.0
Requires-Dist: osp-core >=3.8.0
Requires-Dist: wheel >=0.30.0
Requires-Dist: numpy ==1.20
Requires-Dist: scikit-learn <1,>=0.22.2
Requires-Dist: joblib ==1.1.0
Requires-Dist: parsimonious
Requires-Dist: arcp >=0.2.1
Requires-Dist: minio >=7.1.15
Requires-Dist: reaxpro-wrappers >=2.0.0
Provides-Extra: dev
Requires-Dist: bumpver ==2021.1114 ; extra == 'dev'
Requires-Dist: dunamai ==1.7.0 ; extra == 'dev'
Provides-Extra: pre_commit
Requires-Dist: pre-commit ; extra == 'pre_commit'
Provides-Extra: tests
Requires-Dist: pytest ; extra == 'tests'
Requires-Dist: pytest-cov ; extra == 'tests'
Requires-Dist: pytest-mock ; extra == 'tests'
